signtractions/__init__.py
signtractions/models/__init__.py
signtractions/models/containers.py
signtractions/models/signing.py
signtractions/models/snapshot.py
signtractions/resources/__init__.py
signtractions/resources/command_executor.py
signtractions/resources/exceptions.py
signtractions/resources/fake_quay_client.py
signtractions/resources/fake_signing_wrapper.py
signtractions/resources/quay_client.py
signtractions/resources/quay_session.py
signtractions/resources/reference_constructor.py
signtractions/resources/signing_wrapper.py
signtractions/resources/types.py
signtractions/resources/utils/__init__.py
signtractions/resources/utils/misc.py
signtractions/tractions/__init__.py
signtractions/tractions/containers.py
signtractions/tractions/signing.py
signtractions/tractions/snapshot.py
signtractions/tractors/__init__.py
signtractions/tractors/t_sign_containers.py
signtractions/tractors/t_sign_snapshot.py
signtractions-0.0.5.dist-info/LICENSE
signtractions-0.0.5.dist-info/METADATA
signtractions-0.0.5.dist-info/WHEEL
signtractions-0.0.5.dist-info/entry_points.txt
signtractions-0.0.5.dist-info/top_level.txt
signtractions-0.0.5.dist-info/RECORD
